{
    "poem_title": "Desiring to praise worthily. From the German.",
    "author": "Rev. John Wesley",
    "poem_alt_title": "From the German .",
    "manually_checked": false,
    "stanzas": [
        {
            "stanza_number": 1,
            "stanza_type": "quatrain",
            "lines": [
                {
                    "metrical_pattern": "-+|-+|-+|-+",
                    "line_length": 8,
                    "foot": "iamb",
                    "metre": "tetrameter",
                    "line_number": 1,
                    "line_text": "MONARCH of All, with lowly Fear",
                    "words": [
                        {
                            "word_text": "MONARCH"
                        },
                        {
                            "word_text": "of"
                        },
                        {
                            "word_text": "All"
                        },
                        {
                            "word_text": "with"
                        },
                        {
                            "word_text": "lowly"
                        },
                        {
                            "word_text": "Fear"
                        }
                    ]
                },
                {
                    "metrical_pattern": "-+|-+|-+|-+",
                    "line_length": 8,
                    "foot": "iamb",
                    "metre": "tetrameter",
                    "line_number": 2,
                    "line_text": "To whom Heaven's Host their Voices raise,",
                    "words": [
                        {
                            "word_text": "To"
                        },
                        {
                            "word_text": "whom"
                        },
                        {
                            "word_text": "Heaven's"
                        },
                        {
                            "word_text": "Host"
                        },
                        {
                            "word_text": "their"
                        },
                        {
                            "word_text": "Voices"
                        },
                        {
                            "word_text": "raise"
                        }
                    ]
                },
                {
                    "metrical_pattern": "-+|-+|-+|-+",
                    "line_length": 8,
                    "foot": "iamb",
                    "metre": "tetrameter",
                    "line_number": 3,
                    "line_text": "Even Earth and Dust thy Bounties share:",
                    "words": [
                        {
                            "word_text": "Even"
                        },
                        {
                            "word_text": "Earth"
                        },
                        {
                            "word_text": "and"
                        },
                        {
                            "word_text": "Dust"
                        },
                        {
                            "word_text": "thy"
                        },
                        {
                            "word_text": "Bounties"
                        },
                        {
                            "word_text": "share"
                        }
                    ]
                },
                {
                    "metrical_pattern": "-+|-+|-+|-+",
                    "line_length": 8,
                    "foot": "iamb",
                    "metre": "tetrameter",
                    "line_number": 4,
                    "line_text": "Let Earth and Dust attempt thy Praise.",
                    "words": [
                        {
                            "word_text": "Let"
                        },
                        {
                            "word_text": "Earth"
                        },
                        {
                            "word_text": "and"
                        },
                        {
                            "word_text": "Dust"
                        },
                        {
                            "word_text": "attempt"
                        },
                        {
                            "word_text": "thy"
                        },
                        {
                            "word_text": "Praise"
                        }
                    ]
                }
            ],
            "stanza_text": "MONARCH of All, with lowly Fear\nTo whom Heaven's Host their Voices raise,\nEven Earth and Dust thy Bounties share:\nLet Earth and Dust attempt thy Praise."
        },
        {
            "stanza_number": 2,
            "stanza_type": "quatrain",
            "lines": [
                {
                    "metrical_pattern": "-+|-+|-+|-+",
                    "line_length": 8,
                    "foot": "iamb",
                    "metre": "tetrameter",
                    "line_number": 5,
                    "line_text": "Before thy Face, O LORD most High,",
                    "words": [
                        {
                            "word_text": "Before"
                        },
                        {
                            "word_text": "thy"
                        },
                        {
                            "word_text": "Face"
                        },
                        {
                            "word_text": "O"
                        },
                        {
                            "word_text": "LORD"
                        },
                        {
                            "word_text": "most"
                        },
                        {
                            "word_text": "High"
                        }
                    ]
                },
                {
                    "metrical_pattern": "-+|-+|-+|-+",
                    "line_length": 8,
                    "foot": "iamb",
                    "metre": "tetrameter",
                    "line_number": 6,
                    "line_text": "Sinks all created Glory down:",
                    "words": [
                        {
                            "word_text": "Sinks"
                        },
                        {
                            "word_text": "all"
                        },
                        {
                            "word_text": "created"
                        },
                        {
                            "word_text": "Glory"
                        },
                        {
                            "word_text": "down"
                        }
                    ]
                },
                {
                    "metrical_pattern": "-+|-+|-+|-+",
                    "line_length": 8,
                    "foot": "iamb",
                    "metre": "tetrameter",
                    "line_number": 7,
                    "line_text": "Yet be not wroth with me, that I",
                    "words": [
                        {
                            "word_text": "Yet"
                        },
                        {
                            "word_text": "be"
                        },
                        {
                            "word_text": "not"
                        },
                        {
                            "word_text": "wroth"
                        },
                        {
                            "word_text": "with"
                        },
                        {
                            "word_text": "me"
                        },
                        {
                            "word_text": "that"
                        },
                        {
                            "word_text": "I"
                        }
                    ]
                },
                {
                    "metrical_pattern": "-+|-+|-+|-+",
                    "line_length": 8,
                    "foot": "iamb",
                    "metre": "tetrameter",
                    "line_number": 8,
                    "line_text": "Vile Worm, draw near thy awful Throne.",
                    "words": [
                        {
                            "word_text": "Vile"
                        },
                        {
                            "word_text": "Worm"
                        },
                        {
                            "word_text": "draw"
                        },
                        {
                            "word_text": "near"
                        },
                        {
                            "word_text": "thy"
                        },
                        {
                            "word_text": "awful"
                        },
                        {
                            "word_text": "Throne"
                        }
                    ]
                }
            ],
            "stanza_text": "Before thy Face, O LORD most High,\nSinks all created Glory down:\nYet be not wroth with me, that I\nVile Worm, draw near thy awful Throne."
        },
        {
            "stanza_number": 3,
            "stanza_type": "quatrain",
            "lines": [
                {
                    "metrical_pattern": "-+|-+|-+|-+",
                    "line_length": 8,
                    "foot": "iamb",
                    "metre": "tetrameter",
                    "line_number": 9,
                    "line_text": "Of all Thou the Beginning art,",
                    "words": [
                        {
                            "word_text": "Of"
                        },
                        {
                            "word_text": "all"
                        },
                        {
                            "word_text": "Thou"
                        },
                        {
                            "word_text": "the"
                        },
                        {
                            "word_text": "Beginning"
                        },
                        {
                            "word_text": "art"
                        }
                    ]
                },
                {
                    "metrical_pattern": "-+|-+|-+|-+",
                    "line_length": 8,
                    "foot": "iamb",
                    "metre": "tetrameter",
                    "line_number": 10,
                    "line_text": "Of all things Thou alone the End:",
                    "words": [
                        {
                            "word_text": "Of"
                        },
                        {
                            "word_text": "all"
                        },
                        {
                            "word_text": "things"
                        },
                        {
                            "word_text": "Thou"
                        },
                        {
                            "word_text": "alone"
                        },
                        {
                            "word_text": "the"
                        },
                        {
                            "word_text": "End"
                        }
                    ]
                },
                {
                    "metrical_pattern": "-+|-+|-+|-+",
                    "line_length": 8,
                    "foot": "iamb",
                    "metre": "tetrameter",
                    "line_number": 11,
                    "line_text": "On Thee still fix my stedfast Heart;",
                    "words": [
                        {
                            "word_text": "On"
                        },
                        {
                            "word_text": "Thee"
                        },
                        {
                            "word_text": "still"
                        },
                        {
                            "word_text": "fix"
                        },
                        {
                            "word_text": "my"
                        },
                        {
                            "word_text": "stedfast"
                        },
                        {
                            "word_text": "Heart"
                        }
                    ]
                },
                {
                    "metrical_pattern": "-+|-+|-+|-+",
                    "line_length": 8,
                    "foot": "iamb",
                    "metre": "tetrameter",
                    "line_number": 12,
                    "line_text": "To Thee let all my Actions tend.",
                    "words": [
                        {
                            "word_text": "To"
                        },
                        {
                            "word_text": "Thee"
                        },
                        {
                            "word_text": "let"
                        },
                        {
                            "word_text": "all"
                        },
                        {
                            "word_text": "my"
                        },
                        {
                            "word_text": "Actions"
                        },
                        {
                            "word_text": "tend"
                        }
                    ]
                }
            ],
            "stanza_text": "Of all Thou the Beginning art,\nOf all things Thou alone the End:\nOn Thee still fix my stedfast Heart;\nTo Thee let all my Actions tend."
        },
        {
            "stanza_number": 4,
            "stanza_type": "quatrain",
            "lines": [
                {
                    "metrical_pattern": "-+|-+|-+|-+",
                    "line_length": 8,
                    "foot": "iamb",
                    "metre": "tetrameter",
                    "line_number": 13,
                    "line_text": "Thou, LORD, art Light: Thy Native Ray",
                    "words": [
                        {
                            "word_text": "Thou"
                        },
                        {
                            "word_text": "LORD"
                        },
                        {
                            "word_text": "art"
                        },
                        {
                            "word_text": "Light"
                        },
                        {
                            "word_text": "Thy"
                        },
                        {
                            "word_text": "Native"
                        },
                        {
                            "word_text": "Ray"
                        }
                    ]
                },
                {
                    "metrical_pattern": "-+|-+|-+|-+",
                    "line_length": 8,
                    "foot": "iamb",
                    "metre": "tetrameter",
                    "line_number": 14,
                    "line_text": "No Shade, no Variation knows —",
                    "words": [
                        {
                            "word_text": "No"
                        },
                        {
                            "word_text": "Shade"
                        },
                        {
                            "word_text": "no"
                        },
                        {
                            "word_text": "Variation"
                        },
                        {
                            "word_text": "knows"
                        }
                    ]
                },
                {
                    "metrical_pattern": "-+|-+|-+|-+",
                    "line_length": 8,
                    "foot": "iamb",
                    "metre": "tetrameter",
                    "line_number": 15,
                    "line_text": "On my Dark Soul (Ye Clouds away)",
                    "words": [
                        {
                            "word_text": "On"
                        },
                        {
                            "word_text": "my"
                        },
                        {
                            "word_text": "Dark"
                        },
                        {
                            "word_text": "Soul"
                        },
                        {
                            "word_text": "Ye"
                        },
                        {
                            "word_text": "Clouds"
                        },
                        {
                            "word_text": "away"
                        }
                    ]
                },
                {
                    "metrical_pattern": "-+|-+|-+|-+",
                    "line_length": 8,
                    "foot": "iamb",
                    "metre": "tetrameter",
                    "line_number": 16,
                    "line_text": "The Brightness of thy Face disclose.",
                    "words": [
                        {
                            "word_text": "The"
                        },
                        {
                            "word_text": "Brightness"
                        },
                        {
                            "word_text": "of"
                        },
                        {
                            "word_text": "thy"
                        },
                        {
                            "word_text": "Face"
                        },
                        {
                            "word_text": "disclose"
                        }
                    ]
                }
            ],
            "stanza_text": "Thou, LORD, art Light: Thy Native Ray\nNo Shade, no Variation knows —\nOn my Dark Soul (Ye Clouds away)\nThe Brightness of thy Face disclose."
        },
        {
            "stanza_number": 5,
            "stanza_type": "quatrain",
            "lines": [
                {
                    "metrical_pattern": "-+|-+|-+|-+",
                    "line_length": 8,
                    "foot": "iamb",
                    "metre": "tetrameter",
                    "line_number": 17,
                    "line_text": "Thou, LORD, art Love: from Thee pure Love",
                    "words": [
                        {
                            "word_text": "Thou"
                        },
                        {
                            "word_text": "LORD"
                        },
                        {
                            "word_text": "art"
                        },
                        {
                            "word_text": "Love"
                        },
                        {
                            "word_text": "from"
                        },
                        {
                            "word_text": "Thee"
                        },
                        {
                            "word_text": "pure"
                        },
                        {
                            "word_text": "Love"
                        }
                    ]
                },
                {
                    "metrical_pattern": "-+|-+|-+|-+",
                    "line_length": 8,
                    "foot": "iamb",
                    "metre": "tetrameter",
                    "line_number": 18,
                    "line_text": "Flows forth in unexhausted Streams;",
                    "words": [
                        {
                            "word_text": "Flows"
                        },
                        {
                            "word_text": "forth"
                        },
                        {
                            "word_text": "in"
                        },
                        {
                            "word_text": "unexhausted"
                        },
                        {
                            "word_text": "Streams"
                        }
                    ]
                },
                {
                    "metrical_pattern": "-+|-+|-+|-+",
                    "line_length": 8,
                    "foot": "iamb",
                    "metre": "tetrameter",
                    "line_number": 19,
                    "line_text": "Let me its quickning Influence prove,",
                    "words": [
                        {
                            "word_text": "Let"
                        },
                        {
                            "word_text": "me"
                        },
                        {
                            "word_text": "its"
                        },
                        {
                            "word_text": "quickning"
                        },
                        {
                            "word_text": "Influence"
                        },
                        {
                            "word_text": "prove"
                        }
                    ]
                },
                {
                    "metrical_pattern": "-+|-+|-+|-+",
                    "line_length": 8,
                    "foot": "iamb",
                    "metre": "tetrameter",
                    "line_number": 20,
                    "line_text": "Fill my whole Heart with Sacred Flames.",
                    "words": [
                        {
                            "word_text": "Fill"
                        },
                        {
                            "word_text": "my"
                        },
                        {
                            "word_text": "whole"
                        },
                        {
                            "word_text": "Heart"
                        },
                        {
                            "word_text": "with"
                        },
                        {
                            "word_text": "Sacred"
                        },
                        {
                            "word_text": "Flames"
                        }
                    ]
                }
            ],
            "stanza_text": "Thou, LORD, art Love: from Thee pure Love\nFlows forth in unexhausted Streams;\nLet me its quickning Influence prove,\nFill my whole Heart with Sacred Flames."
        },
        {
            "stanza_number": 6,
            "stanza_type": "quatrain",
            "lines": [
                {
                    "metrical_pattern": "-+|-+|-+|-+",
                    "line_length": 8,
                    "foot": "iamb",
                    "metre": "tetrameter",
                    "line_number": 21,
                    "line_text": "Thou, LORD, art Good, and Thou alone:",
                    "words": [
                        {
                            "word_text": "Thou"
                        },
                        {
                            "word_text": "LORD"
                        },
                        {
                            "word_text": "art"
                        },
                        {
                            "word_text": "Good"
                        },
                        {
                            "word_text": "and"
                        },
                        {
                            "word_text": "Thou"
                        },
                        {
                            "word_text": "alone"
                        }
                    ]
                },
                {
                    "metrical_pattern": "-+|-+|-+|-+",
                    "line_length": 8,
                    "foot": "iamb",
                    "metre": "tetrameter",
                    "line_number": 22,
                    "line_text": "With eager Hope, with warm Desire,",
                    "words": [
                        {
                            "word_text": "With"
                        },
                        {
                            "word_text": "eager"
                        },
                        {
                            "word_text": "Hope"
                        },
                        {
                            "word_text": "with"
                        },
                        {
                            "word_text": "warm"
                        },
                        {
                            "word_text": "Desire"
                        }
                    ]
                },
                {
                    "metrical_pattern": "-+|-+|-+|-+",
                    "line_length": 8,
                    "foot": "iamb",
                    "metre": "tetrameter",
                    "line_number": 23,
                    "line_text": "Thee may I still my Portion own,",
                    "words": [
                        {
                            "word_text": "Thee"
                        },
                        {
                            "word_text": "may"
                        },
                        {
                            "word_text": "I"
                        },
                        {
                            "word_text": "still"
                        },
                        {
                            "word_text": "my"
                        },
                        {
                            "word_text": "Portion"
                        },
                        {
                            "word_text": "own"
                        }
                    ]
                },
                {
                    "metrical_pattern": "-+|-+|-+|-+",
                    "line_length": 8,
                    "foot": "iamb",
                    "metre": "tetrameter",
                    "line_number": 24,
                    "line_text": "To Thee in every Thought aspire.",
                    "words": [
                        {
                            "word_text": "To"
                        },
                        {
                            "word_text": "Thee"
                        },
                        {
                            "word_text": "in"
                        },
                        {
                            "word_text": "every"
                        },
                        {
                            "word_text": "Thought"
                        },
                        {
                            "word_text": "aspire"
                        }
                    ]
                }
            ],
            "stanza_text": "Thou, LORD, art Good, and Thou alone:\nWith eager Hope, with warm Desire,\nThee may I still my Portion own,\nTo Thee in every Thought aspire."
        },
        {
            "stanza_number": 7,
            "stanza_type": "quatrain",
            "lines": [
                {
                    "metrical_pattern": "-+|-+|-+|-+",
                    "line_length": 8,
                    "foot": "iamb",
                    "metre": "tetrameter",
                    "line_number": 25,
                    "line_text": "So shall my every Power to Thee",
                    "words": [
                        {
                            "word_text": "So"
                        },
                        {
                            "word_text": "shall"
                        },
                        {
                            "word_text": "my"
                        },
                        {
                            "word_text": "every"
                        },
                        {
                            "word_text": "Power"
                        },
                        {
                            "word_text": "to"
                        },
                        {
                            "word_text": "Thee"
                        }
                    ]
                },
                {
                    "metrical_pattern": "-+|-+|-+|-+",
                    "line_length": 8,
                    "foot": "iamb",
                    "metre": "tetrameter",
                    "line_number": 26,
                    "line_text": "In Love, Thanks, Praise incessant rise,",
                    "words": [
                        {
                            "word_text": "In"
                        },
                        {
                            "word_text": "Love"
                        },
                        {
                            "word_text": "Thanks"
                        },
                        {
                            "word_text": "Praise"
                        },
                        {
                            "word_text": "incessant"
                        },
                        {
                            "word_text": "rise"
                        }
                    ]
                },
                {
                    "metrical_pattern": "-+|-+|-+|-+",
                    "line_length": 8,
                    "foot": "iamb",
                    "metre": "tetrameter",
                    "line_number": 27,
                    "line_text": "Yea my whole Soul and Flesh shall be",
                    "words": [
                        {
                            "word_text": "Yea"
                        },
                        {
                            "word_text": "my"
                        },
                        {
                            "word_text": "whole"
                        },
                        {
                            "word_text": "Soul"
                        },
                        {
                            "word_text": "and"
                        },
                        {
                            "word_text": "Flesh"
                        },
                        {
                            "word_text": "shall"
                        },
                        {
                            "word_text": "be"
                        }
                    ]
                },
                {
                    "metrical_pattern": "-+|-+|-+|-+",
                    "line_length": 8,
                    "foot": "iamb",
                    "metre": "tetrameter",
                    "line_number": 28,
                    "line_text": "One Holy, Living Sacrifice.",
                    "words": [
                        {
                            "word_text": "One"
                        },
                        {
                            "word_text": "Holy"
                        },
                        {
                            "word_text": "Living"
                        },
                        {
                            "word_text": "Sacrifice"
                        }
                    ]
                }
            ],
            "stanza_text": "So shall my every Power to Thee\nIn Love, Thanks, Praise incessant rise,\nYea my whole Soul and Flesh shall be\nOne Holy, Living Sacrifice."
        },
        {
            "stanza_number": 8,
            "stanza_type": "quatrain",
            "lines": [
                {
                    "metrical_pattern": "-+|-+|-+|-+",
                    "line_length": 8,
                    "foot": "iamb",
                    "metre": "tetrameter",
                    "line_number": 29,
                    "line_text": "LORD GOD of Armies, ceaseless Praise",
                    "words": [
                        {
                            "word_text": "LORD"
                        },
                        {
                            "word_text": "GOD"
                        },
                        {
                            "word_text": "of"
                        },
                        {
                            "word_text": "Armies"
                        },
                        {
                            "word_text": "ceaseless"
                        },
                        {
                            "word_text": "Praise"
                        }
                    ]
                },
                {
                    "metrical_pattern": "-+|-+|-+|-+",
                    "line_length": 8,
                    "foot": "iamb",
                    "metre": "tetrameter",
                    "line_number": 30,
                    "line_text": "In Heaven thy Throne to Thee is given,",
                    "words": [
                        {
                            "word_text": "In"
                        },
                        {
                            "word_text": "Heaven"
                        },
                        {
                            "word_text": "thy"
                        },
                        {
                            "word_text": "Throne"
                        },
                        {
                            "word_text": "to"
                        },
                        {
                            "word_text": "Thee"
                        },
                        {
                            "word_text": "is"
                        },
                        {
                            "word_text": "given"
                        }
                    ]
                },
                {
                    "metrical_pattern": "-+|-+|-+|-+",
                    "line_length": 8,
                    "foot": "iamb",
                    "metre": "tetrameter",
                    "line_number": 31,
                    "line_text": "Here as in Heaven thy Name we raise,",
                    "words": [
                        {
                            "word_text": "Here"
                        },
                        {
                            "word_text": "as"
                        },
                        {
                            "word_text": "in"
                        },
                        {
                            "word_text": "Heaven"
                        },
                        {
                            "word_text": "thy"
                        },
                        {
                            "word_text": "Name"
                        },
                        {
                            "word_text": "we"
                        },
                        {
                            "word_text": "raise"
                        }
                    ]
                },
                {
                    "metrical_pattern": "-+|-+|-+|-+",
                    "line_length": 8,
                    "foot": "iamb",
                    "metre": "tetrameter",
                    "line_number": 32,
                    "line_text": "For where thy Presence Shines, is Heaven.",
                    "words": [
                        {
                            "word_text": "For"
                        },
                        {
                            "word_text": "where"
                        },
                        {
                            "word_text": "thy"
                        },
                        {
                            "word_text": "Presence"
                        },
                        {
                            "word_text": "Shines"
                        },
                        {
                            "word_text": "is"
                        },
                        {
                            "word_text": "Heaven"
                        }
                    ]
                }
            ],
            "stanza_text": "LORD GOD of Armies, ceaseless Praise\nIn Heaven thy Throne to Thee is given,\nHere as in Heaven thy Name we raise,\nFor where thy Presence Shines, is Heaven."
        }
    ],
    "corpus": "ecpa"
}