{
    "poem_title": "Madrigali inediti - CCCXXIV",
    "author": "Giovan Battista, il Vecchio Strozzi",
    "manually_checked": false,
    "stanzas": [
        {
            "stanza_number": 1,
            "stanza_type": null,
            "lines": [
                {
                    "line_number": 1,
                    "line_text": "Di sue nugole il ciel torbide e negre",
                    "metrical_pattern": null,
                    "line_length": null,
                    "words": [
                        {
                            "word_text": "Di"
                        },
                        {
                            "word_text": "sue"
                        },
                        {
                            "word_text": "nugole"
                        },
                        {
                            "word_text": "il"
                        },
                        {
                            "word_text": "ciel"
                        },
                        {
                            "word_text": "torbide"
                        },
                        {
                            "word_text": "e"
                        },
                        {
                            "word_text": "negre"
                        }
                    ]
                },
                {
                    "line_number": 2,
                    "line_text": "io non veggio mai carco,",
                    "metrical_pattern": null,
                    "line_length": null,
                    "words": [
                        {
                            "word_text": "io"
                        },
                        {
                            "word_text": "non"
                        },
                        {
                            "word_text": "veggio"
                        },
                        {
                            "word_text": "mai"
                        },
                        {
                            "word_text": "carco,"
                        }
                    ]
                },
                {
                    "line_number": 3,
                    "line_text": "ch'io fra mio cor non dica, e mi rallegre:",
                    "metrical_pattern": null,
                    "line_length": null,
                    "words": [
                        {
                            "word_text": "ch'io"
                        },
                        {
                            "word_text": "fra"
                        },
                        {
                            "word_text": "mio"
                        },
                        {
                            "word_text": "cor"
                        },
                        {
                            "word_text": "non"
                        },
                        {
                            "word_text": "dica,"
                        },
                        {
                            "word_text": "e"
                        },
                        {
                            "word_text": "mi"
                        },
                        {
                            "word_text": "rallegre:"
                        }
                    ]
                },
                {
                    "line_number": 4,
                    "line_text": "or sarò, lasso, io scarco,",
                    "metrical_pattern": null,
                    "line_length": null,
                    "words": [
                        {
                            "word_text": "or"
                        },
                        {
                            "word_text": "sarò,"
                        },
                        {
                            "word_text": "lasso,"
                        },
                        {
                            "word_text": "io"
                        },
                        {
                            "word_text": "scarco,"
                        }
                    ]
                },
                {
                    "line_number": 5,
                    "line_text": "or forse io vedrò quel celeste arco,",
                    "metrical_pattern": null,
                    "line_length": null,
                    "words": [
                        {
                            "word_text": "or"
                        },
                        {
                            "word_text": "forse"
                        },
                        {
                            "word_text": "io"
                        },
                        {
                            "word_text": "vedrò"
                        },
                        {
                            "word_text": "quel"
                        },
                        {
                            "word_text": "celeste"
                        },
                        {
                            "word_text": "arco,"
                        }
                    ]
                },
                {
                    "line_number": 6,
                    "line_text": "e di mille colori",
                    "metrical_pattern": null,
                    "line_length": null,
                    "words": [
                        {
                            "word_text": "e"
                        },
                        {
                            "word_text": "di"
                        },
                        {
                            "word_text": "mille"
                        },
                        {
                            "word_text": "colori"
                        }
                    ]
                },
                {
                    "line_number": 7,
                    "line_text": "e mille, entro e di fuori,",
                    "metrical_pattern": null,
                    "line_length": null,
                    "words": [
                        {
                            "word_text": "e"
                        },
                        {
                            "word_text": "mille,"
                        },
                        {
                            "word_text": "entro"
                        },
                        {
                            "word_text": "e"
                        },
                        {
                            "word_text": "di"
                        },
                        {
                            "word_text": "fuori,"
                        }
                    ]
                },
                {
                    "line_number": 8,
                    "line_text": "tutto sparso il mio splendido soave",
                    "metrical_pattern": null,
                    "line_length": null,
                    "words": [
                        {
                            "word_text": "tutto"
                        },
                        {
                            "word_text": "sparso"
                        },
                        {
                            "word_text": "il"
                        },
                        {
                            "word_text": "mio"
                        },
                        {
                            "word_text": "splendido"
                        },
                        {
                            "word_text": "soave"
                        }
                    ]
                },
                {
                    "line_number": 9,
                    "line_text": "SMERALDO, o chi n'ha pur sempre la chiave.",
                    "metrical_pattern": null,
                    "line_length": null,
                    "words": [
                        {
                            "word_text": "SMERALDO,"
                        },
                        {
                            "word_text": "o"
                        },
                        {
                            "word_text": "chi"
                        },
                        {
                            "word_text": "n'ha"
                        },
                        {
                            "word_text": "pur"
                        },
                        {
                            "word_text": "sempre"
                        },
                        {
                            "word_text": "la"
                        },
                        {
                            "word_text": "chiave."
                        }
                    ]
                }
            ],
            "stanza_text": "Di sue nugole il ciel torbide e negre\nio non veggio mai carco,\nch'io fra mio cor non dica, e mi rallegre:\nor sarò, lasso, io scarco,\nor forse io vedrò quel celeste arco,\ne di mille colori\ne mille, entro e di fuori,\ntutto sparso il mio splendido soave\nSMERALDO, o chi n'ha pur sempre la chiave."
        }
    ],
    "corpus": "bibit"
}