{
    "poem_title": "THE SILLER CROUN.",
    "author": "Susanna Blamire",
    "manually_checked": false,
    "stanzas": [
        {
            "stanza_number": 1,
            "stanza_type": "octet",
            "lines": [
                {
                    "metrical_pattern": "-+|-+|-+|-+",
                    "line_length": 8,
                    "foot": "iamb",
                    "metre": "tetrameter",
                    "line_number": 1,
                    "line_text": "AND ye shall walk in silk attire,",
                    "words": [
                        {
                            "word_text": "AND"
                        },
                        {
                            "word_text": "ye"
                        },
                        {
                            "word_text": "shall"
                        },
                        {
                            "word_text": "walk"
                        },
                        {
                            "word_text": "in"
                        },
                        {
                            "word_text": "silk"
                        },
                        {
                            "word_text": "attire"
                        }
                    ]
                },
                {
                    "metrical_pattern": "-+|-+|-+",
                    "line_length": 6,
                    "foot": "iamb",
                    "metre": "trimeter",
                    "line_number": 2,
                    "line_text": "And siller hae to spare,",
                    "words": [
                        {
                            "word_text": "And"
                        },
                        {
                            "word_text": "siller"
                        },
                        {
                            "word_text": "hae"
                        },
                        {
                            "word_text": "to"
                        },
                        {
                            "word_text": "spare"
                        }
                    ]
                },
                {
                    "metrical_pattern": "-+|-+|-+|-+",
                    "line_length": 8,
                    "foot": "iamb",
                    "metre": "tetrameter",
                    "line_number": 3,
                    "line_text": "Gin ye'll consent to be his bride,",
                    "words": [
                        {
                            "word_text": "Gin"
                        },
                        {
                            "word_text": "ye'll"
                        },
                        {
                            "word_text": "consent"
                        },
                        {
                            "word_text": "to"
                        },
                        {
                            "word_text": "be"
                        },
                        {
                            "word_text": "his"
                        },
                        {
                            "word_text": "bride"
                        }
                    ]
                },
                {
                    "metrical_pattern": "-+|-+|-+",
                    "line_length": 6,
                    "foot": "iamb",
                    "metre": "trimeter",
                    "line_number": 4,
                    "line_text": "Nor think o' Donald mair.",
                    "words": [
                        {
                            "word_text": "Nor"
                        },
                        {
                            "word_text": "think"
                        },
                        {
                            "word_text": "o'"
                        },
                        {
                            "word_text": "Donald"
                        },
                        {
                            "word_text": "mair"
                        }
                    ]
                },
                {
                    "metrical_pattern": "-+|-+|-+|-+",
                    "line_length": 8,
                    "foot": "iamb",
                    "metre": "tetrameter",
                    "line_number": 5,
                    "line_text": "O wha wad buy a silken goun",
                    "words": [
                        {
                            "word_text": "O"
                        },
                        {
                            "word_text": "wha"
                        },
                        {
                            "word_text": "wad"
                        },
                        {
                            "word_text": "buy"
                        },
                        {
                            "word_text": "a"
                        },
                        {
                            "word_text": "silken"
                        },
                        {
                            "word_text": "goun"
                        }
                    ]
                },
                {
                    "metrical_pattern": "-+|-+|-+",
                    "line_length": 6,
                    "foot": "iamb",
                    "metre": "trimeter",
                    "line_number": 6,
                    "line_text": "Wi' a poor broken heart!",
                    "words": [
                        {
                            "word_text": "Wi'"
                        },
                        {
                            "word_text": "a"
                        },
                        {
                            "word_text": "poor"
                        },
                        {
                            "word_text": "broken"
                        },
                        {
                            "word_text": "heart"
                        }
                    ]
                },
                {
                    "metrical_pattern": "-+|-+|-+|-+",
                    "line_length": 8,
                    "foot": "iamb",
                    "metre": "tetrameter",
                    "line_number": 7,
                    "line_text": "Or what's to me a siller croun,",
                    "words": [
                        {
                            "word_text": "Or"
                        },
                        {
                            "word_text": "what's"
                        },
                        {
                            "word_text": "to"
                        },
                        {
                            "word_text": "me"
                        },
                        {
                            "word_text": "a"
                        },
                        {
                            "word_text": "siller"
                        },
                        {
                            "word_text": "croun"
                        }
                    ]
                },
                {
                    "metrical_pattern": "-+|-+|-+",
                    "line_length": 6,
                    "foot": "iamb",
                    "metre": "trimeter",
                    "line_number": 8,
                    "line_text": "Gin frae my love I part!",
                    "words": [
                        {
                            "word_text": "Gin"
                        },
                        {
                            "word_text": "frae"
                        },
                        {
                            "word_text": "my"
                        },
                        {
                            "word_text": "love"
                        },
                        {
                            "word_text": "I"
                        },
                        {
                            "word_text": "part"
                        }
                    ]
                }
            ],
            "stanza_text": "AND ye shall walk in silk attire,\nAnd siller hae to spare,\nGin ye'll consent to be his bride,\nNor think o' Donald mair.\nO wha wad buy a silken goun\nWi' a poor broken heart!\nOr what's to me a siller croun,\nGin frae my love I part!"
        },
        {
            "stanza_number": 2,
            "stanza_type": "octet",
            "lines": [
                {
                    "metrical_pattern": "-+|-+|-+|-+",
                    "line_length": 8,
                    "foot": "iamb",
                    "metre": "tetrameter",
                    "line_number": 9,
                    "line_text": "The mind wha's every wish is pure",
                    "words": [
                        {
                            "word_text": "The"
                        },
                        {
                            "word_text": "mind"
                        },
                        {
                            "word_text": "wha's"
                        },
                        {
                            "word_text": "every"
                        },
                        {
                            "word_text": "wish"
                        },
                        {
                            "word_text": "is"
                        },
                        {
                            "word_text": "pure"
                        }
                    ]
                },
                {
                    "metrical_pattern": "-+|-+|-+",
                    "line_length": 6,
                    "foot": "iamb",
                    "metre": "trimeter",
                    "line_number": 10,
                    "line_text": "Far dearer is to me;",
                    "words": [
                        {
                            "word_text": "Far"
                        },
                        {
                            "word_text": "dearer"
                        },
                        {
                            "word_text": "is"
                        },
                        {
                            "word_text": "to"
                        },
                        {
                            "word_text": "me"
                        }
                    ]
                },
                {
                    "metrical_pattern": "-+|-+|-+|-+",
                    "line_length": 8,
                    "foot": "iamb",
                    "metre": "tetrameter",
                    "line_number": 11,
                    "line_text": "And ere I'm forc'd to break my faith",
                    "words": [
                        {
                            "word_text": "And"
                        },
                        {
                            "word_text": "ere"
                        },
                        {
                            "word_text": "I'm"
                        },
                        {
                            "word_text": "forc'd"
                        },
                        {
                            "word_text": "to"
                        },
                        {
                            "word_text": "break"
                        },
                        {
                            "word_text": "my"
                        },
                        {
                            "word_text": "faith"
                        }
                    ]
                },
                {
                    "metrical_pattern": "-+|-+|-+",
                    "line_length": 6,
                    "foot": "iamb",
                    "metre": "trimeter",
                    "line_number": 12,
                    "line_text": "I'll lay me doun an' dee!",
                    "words": [
                        {
                            "word_text": "I'll"
                        },
                        {
                            "word_text": "lay"
                        },
                        {
                            "word_text": "me"
                        },
                        {
                            "word_text": "doun"
                        },
                        {
                            "word_text": "an'"
                        },
                        {
                            "word_text": "dee"
                        }
                    ]
                },
                {
                    "metrical_pattern": "-+|-+|-+|-+",
                    "line_length": 8,
                    "foot": "iamb",
                    "metre": "tetrameter",
                    "line_number": 13,
                    "line_text": "For I hae pledg'd my virgin troth",
                    "words": [
                        {
                            "word_text": "For"
                        },
                        {
                            "word_text": "I"
                        },
                        {
                            "word_text": "hae"
                        },
                        {
                            "word_text": "pledg'd"
                        },
                        {
                            "word_text": "my"
                        },
                        {
                            "word_text": "virgin"
                        },
                        {
                            "word_text": "troth"
                        }
                    ]
                },
                {
                    "metrical_pattern": "-+|-+|-+",
                    "line_length": 6,
                    "foot": "iamb",
                    "metre": "trimeter",
                    "line_number": 14,
                    "line_text": "Brave Donald's fate to share;",
                    "words": [
                        {
                            "word_text": "Brave"
                        },
                        {
                            "word_text": "Donald's"
                        },
                        {
                            "word_text": "fate"
                        },
                        {
                            "word_text": "to"
                        },
                        {
                            "word_text": "share"
                        }
                    ]
                },
                {
                    "metrical_pattern": "-+|-+|-+|-+",
                    "line_length": 8,
                    "foot": "iamb",
                    "metre": "tetrameter",
                    "line_number": 15,
                    "line_text": "And he has gi'en to me his heart,",
                    "words": [
                        {
                            "word_text": "And"
                        },
                        {
                            "word_text": "he"
                        },
                        {
                            "word_text": "has"
                        },
                        {
                            "word_text": "gi'en"
                        },
                        {
                            "word_text": "to"
                        },
                        {
                            "word_text": "me"
                        },
                        {
                            "word_text": "his"
                        },
                        {
                            "word_text": "heart"
                        }
                    ]
                },
                {
                    "metrical_pattern": "-+|-+|-+",
                    "line_length": 6,
                    "foot": "iamb",
                    "metre": "trimeter",
                    "line_number": 16,
                    "line_text": "Wi' a' its virtues rare.",
                    "words": [
                        {
                            "word_text": "Wi'"
                        },
                        {
                            "word_text": "a'"
                        },
                        {
                            "word_text": "its"
                        },
                        {
                            "word_text": "virtues"
                        },
                        {
                            "word_text": "rare"
                        }
                    ]
                }
            ],
            "stanza_text": "The mind wha's every wish is pure\nFar dearer is to me;\nAnd ere I'm forc'd to break my faith\nI'll lay me doun an' dee!\nFor I hae pledg'd my virgin troth\nBrave Donald's fate to share;\nAnd he has gi'en to me his heart,\nWi' a' its virtues rare."
        },
        {
            "stanza_number": 3,
            "stanza_type": "octet",
            "lines": [
                {
                    "metrical_pattern": "-+|-+|-+|-+",
                    "line_length": 8,
                    "foot": "iamb",
                    "metre": "tetrameter",
                    "line_number": 17,
                    "line_text": "His gentle manners wan my heart,",
                    "words": [
                        {
                            "word_text": "His"
                        },
                        {
                            "word_text": "gentle"
                        },
                        {
                            "word_text": "manners"
                        },
                        {
                            "word_text": "wan"
                        },
                        {
                            "word_text": "my"
                        },
                        {
                            "word_text": "heart"
                        }
                    ]
                },
                {
                    "metrical_pattern": "-+|-+|-+",
                    "line_length": 6,
                    "foot": "iamb",
                    "metre": "trimeter",
                    "line_number": 18,
                    "line_text": "He gratefu' took the gift;",
                    "words": [
                        {
                            "word_text": "He"
                        },
                        {
                            "word_text": "gratefu'"
                        },
                        {
                            "word_text": "took"
                        },
                        {
                            "word_text": "the"
                        },
                        {
                            "word_text": "gift"
                        }
                    ]
                },
                {
                    "metrical_pattern": "-+|-+|-+|-+",
                    "line_length": 8,
                    "foot": "iamb",
                    "metre": "tetrameter",
                    "line_number": 19,
                    "line_text": "Could I but think to seek it back",
                    "words": [
                        {
                            "word_text": "Could"
                        },
                        {
                            "word_text": "I"
                        },
                        {
                            "word_text": "but"
                        },
                        {
                            "word_text": "think"
                        },
                        {
                            "word_text": "to"
                        },
                        {
                            "word_text": "seek"
                        },
                        {
                            "word_text": "it"
                        },
                        {
                            "word_text": "back"
                        }
                    ]
                },
                {
                    "metrical_pattern": "-+|-+|-+",
                    "line_length": 6,
                    "foot": "iamb",
                    "metre": "trimeter",
                    "line_number": 20,
                    "line_text": "It wad be waur than theft!",
                    "words": [
                        {
                            "word_text": "It"
                        },
                        {
                            "word_text": "wad"
                        },
                        {
                            "word_text": "be"
                        },
                        {
                            "word_text": "waur"
                        },
                        {
                            "word_text": "than"
                        },
                        {
                            "word_text": "theft"
                        }
                    ]
                },
                {
                    "metrical_pattern": "-+|-+|-+|-+",
                    "line_length": 8,
                    "foot": "iamb",
                    "metre": "tetrameter",
                    "line_number": 21,
                    "line_text": "For langest life can ne'er repay",
                    "words": [
                        {
                            "word_text": "For"
                        },
                        {
                            "word_text": "langest"
                        },
                        {
                            "word_text": "life"
                        },
                        {
                            "word_text": "can"
                        },
                        {
                            "word_text": "ne'er"
                        },
                        {
                            "word_text": "repay"
                        }
                    ]
                },
                {
                    "metrical_pattern": "-+|-+|-+",
                    "line_length": 6,
                    "foot": "iamb",
                    "metre": "trimeter",
                    "line_number": 22,
                    "line_text": "The love he bears to me;",
                    "words": [
                        {
                            "word_text": "The"
                        },
                        {
                            "word_text": "love"
                        },
                        {
                            "word_text": "he"
                        },
                        {
                            "word_text": "bears"
                        },
                        {
                            "word_text": "to"
                        },
                        {
                            "word_text": "me"
                        }
                    ]
                },
                {
                    "metrical_pattern": "-+|-+|-+|-+",
                    "line_length": 8,
                    "foot": "iamb",
                    "metre": "tetrameter",
                    "line_number": 23,
                    "line_text": "And ere I'm forc'd to break my troth",
                    "words": [
                        {
                            "word_text": "And"
                        },
                        {
                            "word_text": "ere"
                        },
                        {
                            "word_text": "I'm"
                        },
                        {
                            "word_text": "forc'd"
                        },
                        {
                            "word_text": "to"
                        },
                        {
                            "word_text": "break"
                        },
                        {
                            "word_text": "my"
                        },
                        {
                            "word_text": "troth"
                        }
                    ]
                },
                {
                    "metrical_pattern": "-+|-+|-+",
                    "line_length": 6,
                    "foot": "iamb",
                    "metre": "trimeter",
                    "line_number": 24,
                    "line_text": "I'll lay me doun an' dee.",
                    "words": [
                        {
                            "word_text": "I'll"
                        },
                        {
                            "word_text": "lay"
                        },
                        {
                            "word_text": "me"
                        },
                        {
                            "word_text": "doun"
                        },
                        {
                            "word_text": "an'"
                        },
                        {
                            "word_text": "dee"
                        }
                    ]
                }
            ],
            "stanza_text": "His gentle manners wan my heart,\nHe gratefu' took the gift;\nCould I but think to seek it back\nIt wad be waur than theft!\nFor langest life can ne'er repay\nThe love he bears to me;\nAnd ere I'm forc'd to break my troth\nI'll lay me doun an' dee."
        }
    ],
    "corpus": "ecpa"
}