{
    "manually_checked": false,
    "poem_title": "A Kruger",
    "author": "Ramón Blázquez de Cáceres",
    "poem_alt_title": "De corte en corte mendigando en vano,",
    "corpus": "disco2_1",
    "stanzas": [
        {
            "stanza_number": "1",
            "stanza_type": "cuarteto",
            "lines": [
                {
                    "line_number": "1",
                    "line_text": "De corte en corte mendigando en vano,",
                    "metrical_pattern": "-+-+---+-+-"
                },
                {
                    "line_number": "2",
                    "line_text": "con la fe, como tú, por compañera,",
                    "metrical_pattern": "--+--+---+-"
                },
                {
                    "line_number": "3",
                    "line_text": "recorrió el gran Colón la España entera",
                    "metrical_pattern": "--++-+---+-"
                },
                {
                    "line_number": "4",
                    "line_text": "despreciando su genio soberano.",
                    "metrical_pattern": "--+--+---+-"
                }
            ],
            "stanza_text": "De corte en corte mendigando en vano,\ncon la fe, como tú, por compañera,\nrecorrió el gran Colón la España entera\ndespreciando su genio soberano."
        },
        {
            "stanza_number": "2",
            "stanza_type": "cuarteto",
            "lines": [
                {
                    "line_number": "5",
                    "line_text": "Luchó con fe su espíritu cristiano,",
                    "metrical_pattern": "-+-+-+---+-"
                },
                {
                    "line_number": "6",
                    "line_text": "y siguió resignado su carrera,",
                    "metrical_pattern": "--+--+---+-"
                },
                {
                    "line_number": "7",
                    "line_text": "hasta que el alma de Isabel primera",
                    "metrical_pattern": "---+---+-+-"
                },
                {
                    "line_number": "8",
                    "line_text": "brindóle apoyo con augusta mano.",
                    "metrical_pattern": "-+-+---+-+-"
                }
            ],
            "stanza_text": "Luchó con fe su espíritu cristiano,\ny siguió resignado su carrera,\nhasta que el alma de Isabel primera\nbrindóle apoyo con augusta mano."
        },
        {
            "stanza_number": "3",
            "stanza_type": "terceto",
            "lines": [
                {
                    "line_number": "9",
                    "line_text": "También de corte en corte, tú, infelice",
                    "metrical_pattern": "-+-+-+-+-+-"
                },
                {
                    "line_number": "10",
                    "line_text": "demandando justicia has encontrado",
                    "metrical_pattern": "--+--++--+-"
                },
                {
                    "line_number": "11",
                    "line_text": "otra Reina, cual él, que honra la historia.",
                    "metrical_pattern": "+-+--++--+-"
                }
            ],
            "stanza_text": "También de corte en corte, tú, infelice\ndemandando justicia has encontrado\notra Reina, cual él, que honra la historia."
        },
        {
            "stanza_number": "4",
            "stanza_type": "terceto",
            "lines": [
                {
                    "line_number": "12",
                    "line_text": "Al que ha sed de justicia ahora bendice;",
                    "metrical_pattern": "-++--++--+-"
                },
                {
                    "line_number": "13",
                    "line_text": "y si a Colón dio un mundo, a ti te ha dado",
                    "metrical_pattern": "---+++-+++-"
                },
                {
                    "line_number": "14",
                    "line_text": "en la palma del mártir la victoria.",
                    "metrical_pattern": "--+--+---+-"
                }
            ],
            "stanza_text": "Al que ha sed de justicia ahora bendice;\ny si a Colón dio un mundo, a ti te ha dado\nen la palma del mártir la victoria."
        }
    ]
}